_pgd.cpython-37m-darwin.so
pconfluent/__init__.py
pconfluent/pconfluent.py
pconfluent/swig/__init__.py
pconfluent/swig/pgd.py
pconfluent-0.4.dist-info/LICENSE
pconfluent-0.4.dist-info/METADATA
pconfluent-0.4.dist-info/WHEEL
pconfluent-0.4.dist-info/top_level.txt
pconfluent-0.4.dist-info/RECORD
